learning/README.md
learning/__init__.py
learning/train_jax_ppo.py
learning/train_rsl_rl.py
learning/notebooks/dm_control_suite.ipynb
learning/notebooks/locomotion.ipynb
learning/notebooks/manipulation.ipynb
learning/notebooks/training_vision_1.ipynb
learning/notebooks/training_vision_1_t4.ipynb
learning/notebooks/training_vision_2.ipynb
mujoco_playground/__init__.py
mujoco_playground/_src/__init__.py
mujoco_playground/_src/gait.py
mujoco_playground/_src/mjx_env.py
mujoco_playground/_src/registry.py
mujoco_playground/_src/registry_test.py
mujoco_playground/_src/reward.py
mujoco_playground/_src/wrapper.py
mujoco_playground/_src/wrapper_test.py
mujoco_playground/_src/wrapper_torch.py
mujoco_playground/_src/dm_control_suite/README.md
mujoco_playground/_src/dm_control_suite/__init__.py
mujoco_playground/_src/dm_control_suite/acrobot.py
mujoco_playground/_src/dm_control_suite/ball_in_cup.py
mujoco_playground/_src/dm_control_suite/cartpole.py
mujoco_playground/_src/dm_control_suite/cheetah.py
mujoco_playground/_src/dm_control_suite/common.py
mujoco_playground/_src/dm_control_suite/dm_control_suite_test.py
mujoco_playground/_src/dm_control_suite/finger.py
mujoco_playground/_src/dm_control_suite/fish.py
mujoco_playground/_src/dm_control_suite/hopper.py
mujoco_playground/_src/dm_control_suite/humanoid.py
mujoco_playground/_src/dm_control_suite/pendulum.py
mujoco_playground/_src/dm_control_suite/point_mass.py
mujoco_playground/_src/dm_control_suite/reacher.py
mujoco_playground/_src/dm_control_suite/swimmer.py
mujoco_playground/_src/dm_control_suite/walker.py
mujoco_playground/_src/dm_control_suite/xmls/README.md
mujoco_playground/_src/dm_control_suite/xmls/acrobot.xml
mujoco_playground/_src/dm_control_suite/xmls/ball_in_cup.xml
mujoco_playground/_src/dm_control_suite/xmls/cartpole.xml
mujoco_playground/_src/dm_control_suite/xmls/cheetah.xml
mujoco_playground/_src/dm_control_suite/xmls/finger.xml
mujoco_playground/_src/dm_control_suite/xmls/fish.xml
playground-0.1.0.dist-info/METADATA
playground-0.1.0.dist-info/WHEEL
playground-0.1.0.dist-info/entry_points.txt
playground-0.1.0.dist-info/licenses/LICENSE
playground-0.1.0.dist-info/RECORD
