Metadata-Version: 2.4
Name: playground
Version: 0.1.0
Dynamic: Summary
Author-email: Google DeepMind <mujoco@deepmind.com>
License-File: LICENSE
Keywords: mjx,mujoco,reinforcement learning,sim2real
Classifier: Development Status :: 5 - Production/Stable
Classifier: Framework :: Robot Framework :: Library
Classifier: Intended Audience :: Developers
Classifier: Intended Audience :: Science/Research
Classifier: License :: OSI Approved :: Apache Software License
Classifier: Programming Language :: Python :: 3.10
Classifier: Programming Language :: Python :: 3.11
Classifier: Programming Language :: Python :: 3.12
Classifier: Topic :: Scientific/Engineering
Requires-Python: >=3.10
Requires-Dist: absl-py
Requires-Dist: brax>=0.12.5
Requires-Dist: etils
Requires-Dist: flax
Requires-Dist: jax
Requires-Dist: lxml
Requires-Dist: mediapy
Requires-Dist: ml-collections
Requires-Dist: mujoco-mjx>=3.4
Requires-Dist: mujoco>=3.4
Requires-Dist: orbax-checkpoint>=0.11.22
Requires-Dist: tqdm
Requires-Dist: warp-lang>=1.11
Provides-Extra: all
Requires-Dist: absl-py; extra == 'all'
Requires-Dist: dm-control; extra == 'all'
Requires-Dist: jax[cuda12]; extra == 'all'
Requires-Dist: jupyter; extra == 'all'
Requires-Dist: matplotlib; extra == 'all'
Requires-Dist: mypy; extra == 'all'
Requires-Dist: pre-commit; extra == 'all'
Requires-Dist: pyink; extra == 'all'
Requires-Dist: pylint; extra == 'all'
Requires-Dist: pytest; extra == 'all'
Requires-Dist: pytest-xdist; extra == 'all'
Requires-Dist: pytype; extra == 'all'
Requires-Dist: rsl-rl-lib>=3.0.0; extra == 'all'
Requires-Dist: ruff; extra == 'all'
Requires-Dist: wandb; extra == 'all'
Provides-Extra: cuda
Requires-Dist: jax[cuda12]; extra == 'cuda'
Provides-Extra: dev
Requires-Dist: absl-py; extra == 'dev'
Requires-Dist: dm-control; extra == 'dev'
Requires-Dist: mypy; extra == 'dev'
Requires-Dist: pre-commit; extra == 'dev'
Requires-Dist: pyink; extra == 'dev'
Requires-Dist: pylint; extra == 'dev'
Requires-Dist: pytest; extra == 'dev'
Requires-Dist: pytest-xdist; extra == 'dev'
Requires-Dist: pytype; extra == 'dev'
Requires-Dist: ruff; extra == 'dev'
Provides-Extra: learning
Requires-Dist: rsl-rl-lib>=3.0.0; extra == 'learning'
Requires-Dist: wandb; extra == 'learning'
Provides-Extra: notebooks
Requires-Dist: jupyter; extra == 'notebooks'
Requires-Dist: matplotlib; extra == 'notebooks'
Provides-Extra: test
Requires-Dist: absl-py; extra == 'test'
Requires-Dist: dm-control; extra == 'test'
Requires-Dist: pytest; extra == 'test'
Requires-Dist: pytest-xdist; extra == 'test'
